README.md
helloworld.py
setup.py
my_first_helloworld_script.egg-info/PKG-INFO
my_first_helloworld_script.egg-info/SOURCES.txt
my_first_helloworld_script.egg-info/dependency_links.txt
my_first_helloworld_script.egg-info/top_level.txt