Metadata-Version: 2.1
Name: my-first-helloworld-script
Version: 0.12
Summary: This is my first pip package
Home-page: https://github.com/LeonLian/pipPackagingTest.git
Author: lian zheng
Author-email: lianzheng07@163.com
License: UNKNOWN
Platform: UNKNOWN
